root_dash_lib/__init__.py
root_dash_lib/aggregator.py
root_dash_lib/dash_builder.py
root_dash_lib/data_handler.py
root_dash_lib/data_viewer.py
root_dash_lib/interface.py
root_dash_lib/settings.py
root_dash_lib/user_utils.py
root_dash_lib/utils.py
root_dash_lib/pages/__init__.py
root_dash_lib/pages/base_page.py
src/__init__.py
src/dashboard.py
test/__init__.py
test/test_lib.py
test/test_pipeline.py
test/lib_for_tests/__init__.py
test/lib_for_tests/grants_user_utils.py
test/lib_for_tests/press_user_utils.py
root_dash-1.0.1.dist-info/LICENSE
root_dash-1.0.1.dist-info/METADATA
root_dash-1.0.1.dist-info/WHEEL
root_dash-1.0.1.dist-info/top_level.txt
root_dash-1.0.1.dist-info/RECORD
