Metadata-Version: 2.1
Name: root-dash
Version: 1.0.1
Summary: A package for quick creation of data-science dashboards.
Author-email: Zachary Hafen-Saavedra <z.hafen.saavedra@gmail.com>
Project-URL: Homepage, https://github.com/zhafen/root-dash
Project-URL: Bug Tracker, https://github.com/zhafen/root-dash/issues
Classifier: Programming Language :: Python :: 3
Classifier: License :: OSI Approved :: MIT License
Classifier: Operating System :: OS Independent
Requires-Python: >=3.7
License-File: LICENSE
Requires-Dist: numpy
Requires-Dist: pandas
Requires-Dist: openpyxl
Requires-Dist: matplotlib
Requires-Dist: seaborn
Requires-Dist: PyYAML
Requires-Dist: streamlit
Requires-Dist: pytest
Requires-Dist: jupyterlab
Requires-Dist: nbconvert
Requires-Dist: nbformat
